polarishub/__init__.py
polarishub/api.py
polarishub/command_line.py
polarishub/manage.py
polarishub/setup.py
polarishub/phub/__init__.py
polarishub/phub/settings.py
polarishub/phub/urls.py
polarishub/phub/wsgi.py
polarishub/serverhub/__init__.py
polarishub/serverhub/admin.py
polarishub/serverhub/apps.py
polarishub/serverhub/models.py
polarishub/serverhub/myqrcode.py
polarishub/serverhub/tests.py
polarishub/serverhub/views.py
polarishub/serverhub/migrations/__init__.py
polarishub-0.9.16.dist-info/LICENSE
polarishub-0.9.16.dist-info/METADATA
polarishub-0.9.16.dist-info/WHEEL
polarishub-0.9.16.dist-info/entry_points.txt
polarishub-0.9.16.dist-info/top_level.txt
polarishub-0.9.16.dist-info/RECORD
