Metadata-Version: 2.1
Name: polarishub
Version: 0.9.16
Summary: A p2p file transfer program via LAN.
Home-page: https://github.com/XieGuochao/polarishub
Author: Xie Guochao & Hao Senyue
Author-email: senyuehao@link.cuhk.edu.cn
License: MIT
Platform: UNKNOWN
Classifier: License :: OSI Approved :: MIT License
Classifier: Operating System :: OS Independent
Classifier: Programming Language :: Python
Classifier: Programming Language :: Python :: 3
Classifier: Programming Language :: Python :: 3.6
Classifier: Programming Language :: Python :: 3.7
Requires-Python: >=3.6.0
Requires-Dist: Django (>=2.1.5)
Requires-Dist: MyQR (==2.3.1)
